<?xml version="1.0" encoding="utf-8"?>
<?xml-stylesheet type='text/xsl' href='ConversionLogFile.xsl'?>
<LogFile projectName="Tonhaofinal_V13" typeText="Type" messageText="Message" timeText="Time">
  <MessageCell ServiceId="80" MessageId="30" MessageClass="Information" Timestamp="7/19/2016 3:10:47 PM">
    <Number ServiceNumber="80" MessageNumber="30" />
    <Text FeedbackText="Upgrade started" />
    <Help HelpId="-1" />
  </MessageCell>
  <MessageCell ServiceId="80" MessageId="30" MessageClass="Information" Timestamp="7/19/2016 3:10:47 PM">
    <Number ServiceNumber="80" MessageNumber="30" />
    <Text FeedbackText="Reading information from previous project/library." />
    <Help HelpId="-1" />
  </MessageCell>
  <MessageCell ServiceId="80" MessageId="30" MessageClass="Information" Timestamp="7/19/2016 3:10:52 PM">
    <Number ServiceNumber="80" MessageNumber="30" />
    <Text FeedbackText="Updating new project/library." />
    <Help HelpId="-1" />
  </MessageCell>
  <MessageCell ServiceId="80" MessageId="30" MessageClass="Information" Timestamp="7/19/2016 3:10:57 PM">
    <Number ServiceNumber="80" MessageNumber="30" />
    <Text FeedbackText="Updating new project/library." />
    <Help HelpId="-1" />
  </MessageCell>
  <Details ServiceId="80" MessageId="30" Timestamp="7/19/2016 3:11:02 PM" Debug="false">
    <Text>Preparing conversion of the S7 program for CPU "PLC_1"</Text>
  </Details>
  <Details ServiceId="80" MessageId="30" Timestamp="7/19/2016 3:11:04 PM" Debug="false">
    <Text>Conversion completed.</Text>
  </Details>
  <Details ServiceId="80" MessageId="30" Timestamp="7/19/2016 3:12:20 PM" Debug="false">
    <Text>Converting S7 program for CPU "PLC_1".</Text>
  </Details>
  <Details ServiceId="80" MessageId="30" Timestamp="7/19/2016 3:12:27 PM" Debug="false">
    <Text>Conversion completed.</Text>
  </Details>
  <Details ServiceId="80" MessageId="30" Timestamp="7/19/2016 3:12:27 PM" Debug="false">
    <Text>Preparing conversion of the S7 program for CPU "PLC_1"</Text>
  </Details>
  <Details ServiceId="80" MessageId="30" Timestamp="7/19/2016 3:12:27 PM" Debug="false">
    <Text>Conversion completed.</Text>
  </Details>
  <Details ServiceId="80" MessageId="30" Timestamp="7/19/2016 3:12:27 PM" Debug="false">
    <Text>Converting S7 program for CPU "PLC_1".</Text>
  </Details>
  <Details ServiceId="80" MessageId="30" Timestamp="7/19/2016 3:12:30 PM" Debug="false">
    <Text>Conversion completed.</Text>
  </Details>
  <MessageCell ServiceId="80" MessageId="30" MessageClass="Warning" Timestamp="7/19/2016 3:12:30 PM">
    <Number ServiceNumber="80" MessageNumber="30" />
    <Text FeedbackText="To finish upgrade of the project, select the menu command &quot;Edit &gt; Compile&quot; for each device in the project." />
    <Help HelpId="-1" />
  </MessageCell>
  <MessageCell ServiceId="80" MessageId="30" MessageClass="Information" Timestamp="7/19/2016 3:13:02 PM">
    <Number ServiceNumber="80" MessageNumber="30" />
    <Text FeedbackText="Updating new project/library." />
    <Help HelpId="-1" />
  </MessageCell>
  <MessageCell ServiceId="80" MessageId="30" MessageClass="Information" Timestamp="7/19/2016 3:13:03 PM">
    <Number ServiceNumber="80" MessageNumber="30" />
    <Text FeedbackText="Saving the upgraded project/library." />
    <Help HelpId="-1" />
  </MessageCell>
  <MessageCell ServiceId="Automation-ObjectFrame-Feedbacks" MessageId="ConversionInfoTabProjectSucceeded" MessageClass="Success" Timestamp="7/19/2016 3:13:06 PM">
    <Number ServiceNumber="80" MessageNumber="34" />
    <Text FeedbackText="Project 'Tonhaofinal' was successfully upgraded and saved as project 'Tonhaofinal_V13'." />
    <Help HelpId="-1" HelpFile="" />
  </MessageCell>
</LogFile>